joinly_common/__init__.py
joinly_common/py.typed
joinly_common/types.py
joinly_common-0.1.3.dist-info/METADATA
joinly_common-0.1.3.dist-info/WHEEL
joinly_common-0.1.3.dist-info/RECORD
