Metadata-Version: 2.4
Name: joinly-common
Version: 0.1.3
Summary: Common library for joinly: Make your meetings accessible to AI Agents
Project-URL: Repository, https://github.com/joinly-ai/joinly
Author-email: dbrockmann <dominik@joinly.ai>
Requires-Python: >=3.12
Requires-Dist: pydantic>=2.11.7
